yamllintelerir/__init__.py
yamllintelerir/__main__.py
yamllintelerir/cli.py
yamllintelerir/config.py
yamllintelerir/linter.py
yamllintelerir/parser.py
yamllintelerir/conf/default.yaml
yamllintelerir/conf/relaxed.yaml
yamllintelerir/rules/__init__.py
yamllintelerir/rules/braces.py
yamllintelerir/rules/brackets.py
yamllintelerir/rules/colons.py
yamllintelerir/rules/commas.py
yamllintelerir/rules/comments.py
yamllintelerir/rules/comments_indentation.py
yamllintelerir/rules/common.py
yamllintelerir/rules/document_end.py
yamllintelerir/rules/document_start.py
yamllintelerir/rules/empty_lines.py
yamllintelerir/rules/empty_values.py
yamllintelerir/rules/hyphens.py
yamllintelerir/rules/indentation.py
yamllintelerir/rules/key_duplicates.py
yamllintelerir/rules/key_ordering.py
yamllintelerir/rules/line_length.py
yamllintelerir/rules/new_line_at_end_of_file.py
yamllintelerir/rules/new_lines.py
yamllintelerir/rules/octal_values.py
yamllintelerir/rules/quoted_strings.py
yamllintelerir/rules/trailing_spaces.py
yamllintelerir/rules/truthy.py
yamllintelerir-1.17.14.dist-info/LICENSE
yamllintelerir-1.17.14.dist-info/METADATA
yamllintelerir-1.17.14.dist-info/WHEEL
yamllintelerir-1.17.14.dist-info/entry_points.txt
yamllintelerir-1.17.14.dist-info/top_level.txt
yamllintelerir-1.17.14.dist-info/RECORD
